{"body":{"title":"Frontend Developer","description":"We are looking for a skilled Frontend Developer with experience in React and TypeScript to join our team.","location":"Ahmedabad, India","jobType":"full-time","salary":{"min":500000,"max":1200000,"currency":"INR"},"experience":"1-2 years","skillsRequired":["React","TypeScript","CSS","git"],"openings":4,"deadline":"2026-03-30","company":"69b8eb1bb6564d680e6821e9"},"validData":{"title":"Frontend Developer","description":"We are looking for a skilled Frontend Developer with experience in React and TypeScript to join our team.","company":"69b8eb1bb6564d680e6821e9","location":"Ahmedabad, India","jobType":"full-time","salary":{"min":500000,"max":1200000,"currency":"INR"},"experience":"1-2 years","skillsRequired":["React","TypeScript","CSS","git"],"openings":4,"deadline":"2026-03-30T00:00:00.000Z"}}